flake8_ensure_ascii.py
flake8_ensure_ascii-1.0.0.dist-info/LICENSE
flake8_ensure_ascii-1.0.0.dist-info/METADATA
flake8_ensure_ascii-1.0.0.dist-info/WHEEL
flake8_ensure_ascii-1.0.0.dist-info/entry_points.txt
flake8_ensure_ascii-1.0.0.dist-info/top_level.txt
flake8_ensure_ascii-1.0.0.dist-info/RECORD
